{
  "id": "bahrain",
  "name": "Bahrain",
  "type": "country",
  "created": "2026-03-23",
  "last_updated": "2026-06-11",
  "summary": "Day 103 / 2026-06-10 (Wednesday): **FIFTH FLEET HQ STRUCK AGAIN BY IRANIAN DRONES/MISSILES — INTERCEPTED, ZERO DAMAGE PER US, IRGC HIT-CLAIM DENIED; GULF MARKETS STAYED CALM (TADAWUL +0.4%).** (intel A5, A9) On June 10 (live) the IRGC launched drones/missiles at three US-allied targets — the **US Fifth Fleet HQ in Bahrain**, Ali Al Salem airbase in Kuwait, and — for the FIRST time — Azraq airbase in Jordan. The IRGC CLAIMED 21 targets and 4 destroyed (incl an F-35 hangar + a downed MQ-9). AGAINST that: a US official said NO injuries to US personnel and NO damage to US facilities; the US 'intercepted nearly all missiles and drones' (CONFIRMED non-event for Bahrain — intercepted, zero damage; the Fifth-Fleet-HQ hit is a CLAIMED, US-DENIED Iranian assertion — do NOT elevate). This is the THIRD iteration of the established pattern (June 5-6 Kuwait/Bahrain barrage; the CENTCOM-denied Fifth Fleet claim; now this): spectacular claims, intercepted reality, zero casualties — performative-deterrence strikes. The genuinely new element is JORDAN (a non-Gulf Arab US ally struck for the first time), not Bahrain. The Arab League (Aboul Gheit) condemned the 'brutal' attacks, declared 'full solidarity,' and accused Iran of 'seeking to escalate confrontation with Arab states'; the Arab Parliament condemned likewise — but NO expulsions, NO downgrades, NO Article-51 invocations (words-not-actions continues). MARKETS: Gulf equity stayed calm despite the strikes — Saudi Tadawul +0.4% on the day; no Bahrain-specific risk re-pricing. COMMODITY LATENT RISK: Bahrain's ALBA aluminium smelter (Lines 1-3) remains OFFLINE since mid-March (the Hormuz-closure response); aluminium hit a 4-year high June 2 then unwound -9.4% on the Israel-Iran stand-down — the ALBA non-restart is a latent re-pricing risk if the stand-down breaks. **TRIGGER DECISIONS (June 10)**: NO Bahrain trigger moves — the salvo was intercepted with zero damage/casualties (CONFIRMED via US official); the Fifth-Fleet-HQ hit is an IRGC CLAIM the US denies; the resolved May-9-arrest-sweep trigger is untouched by a kinetic strike. STAY WATCHING (intercepted, zero-casualty). PRIOR — 2026-06-07 (Sunday): **BAHRAIN IS NOW SET TO BE REBUILT WITH IRAN'S MONEY — AND THE UAE JOINED BAHRAIN/KUWAIT IN CONDEMNING IRAN'S BARRAGE.** (intel B1/A3) Treasury Secretary Bessent reportedly directed his department (6 Jun) to fund Gulf-ally reconstruction from FROZEN IRANIAN ASSETS, assessing war-damage costs since 28 Feb — Bahrain among the targeted states (it intercepted missiles and drones on 5-6 June and activated air-raid sirens) — giving Bahrain a concrete material stake in the US refusal to return the $24bn to Tehran (CONFIRMED policy action). Diplomatically the GCC condemnation WIDENED: the UAE denounced the targeting of Kuwait and Bahrain 'in the strongest terms.' The weekend was quiet for Bahrain kinetically (6-Jun evening was drones near Hormuz; zero casualties). Day 99 (Saturday June 6; covers 4 June afternoon -> 5 June US session -> 5-6 June overnight Gulf exchange). **BAHRAIN TARGETED AGAIN AND ACTIVATED AIR-RAID SIRENS — BUT THE SALVO WAS INTERCEPTED/MISSED WITH ZERO CASUALTIES, AND THE IRGC'S FIFTH-FLEET-HQ HIT CLAIM IS ONCE MORE CENTCOM-DENIED.** Overnight 5-6 June Iran fired 7 ballistic missiles at Kuwait and Bahrain (plus 4 one-way attack drones toward Hormuz); US forces intercepted 6 of 7 missiles, the 7th MISSED, ZERO casualties, and struck Iranian coastal radar at Goruk + Qeshm Island in self-defence (intel A3, CONFIRMED). Bahrain activated air-raid sirens. The IRGC FALSELY claimed (CENTCOM-DENIED — do NOT elevate) to have struck the US Fifth Fleet HQ in Bahrain (and the Ali Al Salem airbase in Kuwait); CENTCOM says all Iranian attacks on US forces failed and no US assets were harmed. CBS confirms this exchange is SEPARATE from and SMALLER than the 3-June Kuwait-airport attack (11 projectiles vs ~30, zero deaths vs one) — Iran reverted to the calibrated/zero-casualty template after the 3-June calibration-break. **No Bahrain trigger moves to active — the salvo was intercepted/missed, zero-casualty; the Fifth-Fleet-HQ hit is a CENTCOM-denied Iranian claim.** PRIOR — Day 97 (Thursday June 4; covers 3 June afternoon -> 4 June US day / 5 June IST). **BAHRAIN JOINED THE GULF CONDEMNATION AFTER BEING TARGETED — BUT, LIKE THE REST OF THE GCC EXCEPT KUWAIT, TOOK NO PARALLEL DIPLOMATIC ACTION.** Having intercepted the 3 June Iranian missiles/drones on its own soil (zero casualties; the IRGC's 'Fifth Fleet HQ hit' claim CENTCOM-denied), Bahrain expressed full solidarity within the GCC's collective condemnation of the attacks on Kuwait and Bahrain (Sec-Gen Albudaiwi: 'security of Kuwait and Bahrain is inseparable from Gulf security,' calling for 'a firm international response'; Qatar reversed to condemn) — but did NOT follow Kuwait's expulsion of Iranian diplomats. The rhetoric-vs-action split holds: condemnation across the bloc, Kuwait-only diplomatic rupture. No Bahrain trigger moves. PRIOR — Day 96 (Wednesday June 3; covers 2 June afternoon -> 3 June morning). **BAHRAIN WAS DIRECTLY TARGETED IN THE 3 JUNE BARRAGE — ITS DEFENCE FORCE INTERCEPTED 3 IRANIAN MISSILES AND A NUMBER OF DRONES AIMED AT 'CIVILIAN SITES,' NO CASUALTIES; THE IRGC FALSELY CLAIMED IT HIT THE US FIFTH FLEET HQ.** Bahrain's Defence Force General Command said it intercepted three Iranian missiles and several drones aimed at 'civilian sites,' with no casualties reported. The IRGC claimed it had struck 'the headquarters of the US Fifth Fleet in Bahrain' (Manama) — CENTCOM explicitly rejected the claim as FALSE, stating all Iranian attacks on US forces failed and no US personnel or assets were harmed (intel B3; a clean 'one-side's-framing-as-fact' case). Bahrain — which hosts the US Fifth Fleet — was thus a direct interception party in the cycle's first casualty-producing barrage, but absorbed the strikes with no damage/casualties (the lethal damage landed on Kuwait's civilian airport). Watch whether Bahrain escalates its rhetoric toward Iran after being targeted on its own soil (a possible follow to Kuwait's diplomat expulsion), or holds a quieter posture. **No Bahrain trigger moves to active — the strikes were intercepted, zero-casualty; the Fifth-Fleet-HQ hit is a CENTCOM-denied Iranian CLAIM.** PRIOR — Day 73-74 (Mon-Tue May 11-12). **A5 BAHRAIN 41 IRGC-LINKED DETENTIONS FOLLOW-UP UNCHANGED — no new MoI announcements May 11-12; Iran has not commented publicly. No further Gulf-state internal action announced (no new UAE/Kuwait/Saudi arrests, no new airspace closures). UAE airspace restrictions imposed May 5 ended on/around May 11 (PRE-confirmed timeline). The May 9 arrest sweep remains the singular Gulf-internal action of the cycle; the 'second Gulf-state arrest sweep within 14 days' trigger from May 10 sits at Day 2 of 14, UNTRIPPED.** PRIOR FRAMING (preserved): Bahrain MoI announced May 9 arrest of 41 alleged IRGC-linked individuals — first major Gulf-state internal action against alleged IRGC network during cycle. Bahrain hosts US Fifth Fleet. The Gulf-state response to Iran continues openly bifurcated: Bahrain (pro-US, anti-IRGC), Saudi Arabia (deniable-pro-US-operationally, public-pro-mediation), UAE (covert third combatant per WSJ Lavan), Qatar (substantive mediator via IRGC contacts), Oman (silent mediator), Kuwait (denied airspace). **BAHRAIN MoI ANNOUNCED MAY 9 IT HAD ARRESTED 41 ALLEGED IRGC-LINKED INDIVIDUALS — FIRST MAJOR GULF-STATE INTERNAL ACTION AGAINST ALLEGED IRGC NETWORK DURING THE CYCLE.** Suspects had 'direct contact' with the IRGC and had collected funds intended to be sent to Iran. Investigations continue; further action anticipated (CONFIRMED — Khaleej Times primary, Washington Post, PBS NewsHour, Spectrum News, Anchorage Daily News, Inquirer/AP). Rights groups (HRW, others) argue Bahrain is using the war as cover to crack down on dissent generally — Bahrain hosts US Fifth Fleet and has historical Sunni-government / Shia-majority tensions where the regime has previously used 'Iran proxy' framing against Shia opposition (REPORTED — rights-group framing). **Two readings:** (a) substantive intelligence breakthrough — Bahrain has located IRGC funding/operational network and is dismantling it; (b) opportunistic crackdown using war as pretext — consistent with Bahrain's pattern. The truth may be both. Either way, this is a Gulf-state SIGNAL: Bahrain publicly aligning with the US blockade narrative against Iran, contrasting with Saudi Arabia's deniability-plus-Pakistan-alignment posture and Qatar's emergent IRGC-channel mediator role. **The Gulf-state response to Iran is now openly bifurcated:** Bahrain (pro-US, anti-IRGC), Saudi Arabia (deniable-pro-US-operationally, public-pro-mediation), UAE (continues hawkish per yesterday), Qatar (now openly mediating with IRGC contacts), Oman (silent mediator), Kuwait (denied airspace per WSJ scoop). PRIOR FRAMING (preserved): cumulative damage envelope from earlier cycle — 5th Fleet HQ, Bapco, ALBA, Batelco/AWS — still in effect.",
  "current": {},
  "active_triggers": [
    {
      "condition": "Second Gulf-state-led arrest sweep of alleged IRGC-affiliated network within 14 days (by 2026-05-24) following Bahrain's May 9 41-detentions — confirms US-led intel-sharing-and-disruption campaign against IRGC funding/operational architecture in Gulf",
      "status": "resolved",
      "cascade": [
        "bahrain",
        "iran",
        "united-states",
        "saudi-arabia",
        "uae"
      ],
      "added": "2026-05-10",
      "note_2026-06-03": "RESOLVED untripped. The 14-day window (by 2026-05-24) closed with no second Gulf-state IRGC-network arrest sweep following Bahrain's May 9 detentions — the predicted US-led intel-sharing-and-disruption campaign against IRGC funding architecture did not materialise across the Gulf. Marked resolved on overdue-node refresh (node had been stale since 12 May).",
      "note_2026-06-06": "Unchanged — STAYS RESOLVED. The 5-6 June overnight salvo against Bahrain (intercepted/missed, zero casualties) is a kinetic event, not an internal IRGC-network arrest sweep; it does not bear on this trigger.",
      "note_2026-06-10": "Unchanged — STAYS RESOLVED. The June 10 IRGC strike on the Fifth Fleet HQ (intercepted, zero damage per US official; IRGC hit-claim denied) is a kinetic performative-deterrence event, not an internal IRGC-network arrest sweep; it does not bear on this trigger."
    }
  ],
  "top_edges": [
    {
      "to": "iran",
      "type": "jun10_irgc_third_iteration_drones_missiles_at_fifth_fleet_hq_intercepted_zero_damage_per_us_irgc_hit_claim_denied_performative_deterrence",
      "weight": 10.0,
      "directness": 1,
      "last_activated": "2026-06-11",
      "activation_count": 15,
      "context": "2026-06-11: Second-wave ballistic missiles at Sheikh Isa airbase; 11-yr-old injured by intercepted-drone shrapnel. Absorb-intercept-condemn-mediate pattern holds."
    },
    {
      "to": "united-states",
      "type": "jun10_fifth_fleet_hq_struck_again_intercepted_zero_damage_per_us_official_irgc_hit_claim_denied",
      "weight": 10.0,
      "directness": 1,
      "last_activated": "2026-06-10",
      "activation_count": 11,
      "context": "2026-06-10: IRGC AGAIN claimed to have hit the US Fifth Fleet HQ in Manama (part of a CLAIMED 21-target / 4-destroyed battle-damage list incl an F-35 hangar) — a US official said there were NO injuries to US personnel and NO damage to US facilities; the US intercepted nearly all missiles and drones. NO weight on the denied claim; weight held at 10.0 on the confirmed 'Fifth Fleet host targeted, intercepted, zero-damage' fact."
    }
  ],
  "recent_signals": [
    {
      "date": "2026-06-11",
      "headline": "Hit in Iran's SECOND wave -- ballistic missiles at the Sheikh Isa airbase; an 11-year-old girl injured and property damage in Hamad City/Manama from intercepted-drone shrapnel. Response stayed in the established pattern: absorb, intercept, condemn, mediate -- no expulsion, no downgrade. Saudi Arabia and Qatar signaled 'diplomacy still possible' after the wave.",
      "sources": [
        "Al Jazeera Day 104",
        "Bahraini official statements",
        "Jerusalem Post (Saudi-Qatar)"
      ],
      "verification": "CONFIRMED"
    },
    {
      "date": "2026-06-10",
      "headline": "**FIFTH FLEET HQ STRUCK AGAIN — IRGC DRONES/MISSILES INTERCEPTED, ZERO DAMAGE PER US OFFICIAL, HIT-CLAIM DENIED; GULF MARKETS CALM (TADAWUL +0.4%).** On June 10 the IRGC launched drones/missiles at the US Fifth Fleet HQ in Bahrain (alongside Ali Al Salem/Kuwait and, for the first time, Azraq/Jordan). The IRGC CLAIMED 21 targets and 4 destroyed (incl an F-35 hangar + a downed MQ-9); AGAINST that, a US official said NO injuries to US personnel and NO damage to US facilities, and the US 'intercepted nearly all' missiles and drones. THIRD iteration of the established pattern (June 5-6 barrage; the CENTCOM-denied Fifth Fleet claim; now this) — spectacular claims, intercepted reality, zero casualties = performative deterrence; the genuinely new element is Jordan (first non-Gulf Arab ally struck), not Bahrain. The Arab League (Aboul Gheit) condemned the 'brutal' attacks and accused Iran of 'seeking to escalate confrontation with Arab states' — but NO expulsions, NO downgrades, NO Article-51 invocations. Gulf equity stayed calm (Saudi Tadawul +0.4%). Latent risk: Bahrain's ALBA aluminium smelter (Lines 1-3) remains offline since mid-March; aluminium hit a 4-year high June 2 then unwound -9.4% on the Israel-Iran stand-down — ALBA non-restart is a latent re-pricing risk.",
      "sources": [
        "Intel dossier 2026-06-10 A5, A9 (IRGC strikes on Fifth Fleet HQ/Bahrain, Ali Al Salem/Kuwait, Azraq/Jordan; IRGC claim 21 targets / 4 destroyed)",
        "US official — NO injuries to US personnel, NO damage to US facilities; US intercepted nearly all missiles/drones",
        "Arab League (Aboul Gheit) / Arab Parliament — condemnation of 'brutal' attacks, 'full solidarity,' Iran 'seeking to escalate confrontation with Arab states'",
        "Markets — Saudi Tadawul +0.4%; aluminium 4-year high June 2 then -9.4% unwind; ALBA Lines 1-3 offline since mid-March"
      ],
      "verification": "Fifth Fleet HQ targeted + intercepted, zero damage/casualties = CONFIRMED (US official); IRGC '21 targets / 4 destroyed incl F-35 hangar + MQ-9' = CLAIMED, US-DENIED (no weight); THIRD-iteration performative-deterrence read = STRUCTURAL ANALYSIS; Jordan first-time strike = the genuinely new element; Tadawul +0.4% / aluminium tape = CONFIRMED market data; ALBA offline = CONFIRMED carried structural. No trigger to active (intercepted, zero-casualty)."
    },
    {
      "date": "2026-06-07",
      "headline": "**BAHRAIN TO BE REBUILT WITH IRANIAN MONEY; UAE JOINS THE GCC CONDEMNATION.** Treasury's 6-June move to fund Gulf-ally reconstruction from frozen Iranian assets covers Bahrain (which intercepted the 5-6 June barrage and sounded air-raid sirens), giving it a material stake in Washington's refusal to return the $24bn to Tehran (CONFIRMED policy action; intel B1). The GCC condemnation widened — the UAE denounced the targeting of Kuwait and Bahrain 'in the strongest terms' (intel A3). No fresh Bahrain hit over the weekend; the 6-Jun evening event was drones near Hormuz, zero casualties.",
      "sources": [
        "CBS News (6 Jun)",
        "Jewish Insider (6 Jun)",
        "ABC News live (6 Jun)",
        "Business Standard/Arab News/Reuters (7 Jun)",
        "ABC News (6 Jun, CENTCOM)",
        "The National/Al Jazeera/UPI (6 Jun)"
      ],
      "verification": "CONFIRMED (Treasury action; UAE condemnation multi-sourced)"
    },
    {
      "date": "2026-06-06",
      "headline": "**BAHRAIN TARGETED AGAIN AND ACTIVATED AIR-RAID SIRENS — 7-MISSILE SALVO AT KUWAIT/BAHRAIN (5-6 JUNE), 6 INTERCEPTED, 7TH MISSED, ZERO CASUALTIES; IRGC FIFTH-FLEET-HQ HIT CLAIM CENTCOM-DENIED AGAIN.** Overnight 5-6 June Iran fired 7 ballistic missiles at Kuwait and Bahrain (plus 4 drones toward Hormuz); US forces intercepted 6 of 7 missiles, the 7th missed, ZERO casualties, and struck Iranian coastal radar at Goruk + Qeshm Island in self-defence. Bahrain activated air-raid sirens. The IRGC claimed it struck the US Fifth Fleet HQ in Manama; CENTCOM rejected the claim as FALSE (all Iranian attacks on US forces failed, no US assets harmed). CBS confirms this exchange is SEPARATE from and SMALLER than the 3-June Kuwait-airport attack (11 projectiles vs ~30, zero deaths vs one) — Iran reverted to the calibrated/zero-casualty playbook.",
      "sources": [
        "CENTCOM / US military (official) — 6/7 missiles intercepted, 7th missed, US self-defence strikes on Goruk + Qeshm coastal radar",
        "Bahrain (air-raid sirens activated)",
        "CBS News — exchange SEPARATE from and SMALLER than 3-June Kuwait-airport attack (11 vs ~30 projectiles, zero deaths)",
        "IRGC / Tasnim — claim of US Fifth Fleet HQ hit (Iran claim, CENTCOM-denied)",
        "Intel dossier 2026-06-06 A3"
      ],
      "verification": "7-missile salvo at Kuwait/Bahrain + interception (6 of 7, 7th missed) + air-raid sirens + US defensive strikes + ZERO casualties = CONFIRMED ACTION (CENTCOM + CBS); SIGNIFICANCE = Iran reverted to calibrated/zero-casualty template (smaller than 3 June); IRGC 'Fifth Fleet HQ hit' = CLAIMED, CENTCOM-DENIED (no weight)."
    },
    {
      "date": "2026-06-03",
      "headline": "**BAHRAIN DIRECTLY TARGETED IN THE 3 JUNE BARRAGE — BDF INTERCEPTED 3 IRANIAN MISSILES AND A NUMBER OF DRONES AIMED AT 'CIVILIAN SITES,' NO CASUALTIES; IRGC FALSELY CLAIMED A FIFTH FLEET HQ HIT.** Bahrain's Defence Force General Command said it intercepted three Iranian missiles and several drones aimed at civilian sites, no casualties. The IRGC claimed it struck the US Fifth Fleet HQ in Manama; CENTCOM rejected the claim as FALSE (all attacks on US forces failed, no US assets harmed). Bahrain (Fifth Fleet host) was a direct interception party in the cycle's first casualty-producing barrage but absorbed the strikes cleanly — the lethal damage landed on Kuwait's civilian airport.",
      "sources": [
        "Bahrain Defence Force General Command (official) — 3 missiles + drones intercepted, no casualties",
        "CENTCOM via Gulf News / The National / RFE/RL — Fifth-Fleet-HQ claim FALSE, no US assets harmed",
        "IRGC / Tasnim — claim of Fifth Fleet HQ hit (Iran claim)",
        "Intel dossier 2026-06-03 A1, B3"
      ],
      "verification": "BDF interception of 3 missiles + drones, zero casualties = CONFIRMED ACTION; IRGC 'Fifth Fleet HQ hit' = CLAIMED, CENTCOM says FALSE (no weight)."
    },
    {
      "date": "2026-05-10",
      "headline": "BAHRAIN MOI ANNOUNCED MAY 9 IT HAD ARRESTED 41 ALLEGED IRGC-LINKED INDIVIDUALS — FIRST MAJOR GULF-STATE INTERNAL ACTION AGAINST ALLEGED IRGC NETWORK DURING THE CYCLE. Suspects had 'direct contact' with IRGC and had collected funds intended to be sent to Iran; investigations continue, further action anticipated. Rights groups argue Bahrain may be using war as cover to crack down on dissent generally (Bahrain hosts US Fifth Fleet, historical Sunni-government / Shia-majority tensions). Two readings: (a) substantive intelligence breakthrough; (b) opportunistic crackdown. Either way, Bahrain is publicly aligning with US blockade narrative against Iran. Gulf-state response to Iran now openly bifurcated: Bahrain (pro-US, anti-IRGC), Saudi (deniable-pro-US, public-pro-mediation), UAE (hawkish), Qatar (mediating with IRGC contacts), Oman (silent), Kuwait (denied airspace).",
      "sources": [
        "Khaleej Times (Bahrain MoI primary cite)",
        "Washington Post May 9",
        "PBS NewsHour",
        "Spectrum News",
        "Anchorage Daily News (AP)",
        "Inquirer / AP (rights-group framing)",
        "Human Rights Watch (rights framing)"
      ],
      "verification": "CONFIRMED ACTION — 41 arrests, public Bahrain MoI statement (Khaleej Times primary, Washington Post + PBS + AP wire pickup multi-source); Iran has NOT commented publicly; rights-group alternative framing = REPORTED (HRW, others)"
    }
  ],
  "historical_summaries": [
    {
      "period": "2026-02",
      "summary": "1 signals. Iranian strikes targeted US Navy 5th Fleet HQ in Manama and Crowne Plaza Hotel",
      "signal_count": 1,
      "auto": true
    },
    {
      "period": "2026-03",
      "summary": "3 signals. Bahrain's Bapco declared force majeure after waves of Iranian strikes targeted energy installations | Air raid sirens activated across Bahrain early Sunday March 29 | IRGC struck ALBA aluminum plant (world's largest smelter) — 2 mildly injured, damage assessed",
      "signal_count": 3,
      "auto": true
    },
    {
      "period": "2026-04",
      "summary": "9 signals. IRGC missiles hit Batelco telecommunications facility in Hamala, Bahrain on April 1 — the facility hosts Amazon Web Services infrastructure | IRGC struck Batelco telecommunications facility in Hamala, Bahrain on April 1 — hosts AWS cloud infrastructure, servers rendered 'partly ino | CONFIRMED: Bahrain's Bapco Energies oil storage tank hit by Iranian drone attack on April 5",
      "signal_count": 9,
      "auto": true
    }
  ]
}